{
  "accountAssociation": {
    "header": "REPLACE_AFTER_DEPLOYMENT",
    "payload": "REPLACE_AFTER_DEPLOYMENT",
    "signature": "REPLACE_AFTER_DEPLOYMENT"
  },
  "baseBuilder": {
    "ownerAddress": "REPLACE_WITH_BASE_ACCOUNT_ADDRESS"
  },
  "miniapp": {
    "version": "1",
    "name": "Glisk",
    "homeUrl": "https://glisk.xyz",
    "iconUrl": "https://glisk.xyz/full_logo.svg",
    "splashImageUrl": "https://glisk.xyz/android-chrome-512x512.png",
    "splashBackgroundColor": "#000000",
    "subtitle": "AI-Generated NFTs on Base",
    "description": "Mint unique AI-generated NFTs using creators' custom prompts. Discover top creators, connect your wallet, and collect one-of-a-kind digital art on Base.",
    "primaryCategory": "social",
    "tags": ["nft", "ai", "art", "base", "web3"],
    "screenshotUrls": [],
    "heroImageUrl": "https://glisk.xyz/android-chrome-512x512.png",
    "tagline": "Create & Collect AI Art NFTs",
    "ogTitle": "Glisk - AI NFT Platform",
    "ogDescription": "Mint AI-generated NFTs from top creators on Base blockchain",
    "ogImageUrl": "https://glisk.xyz/android-chrome-512x512.png",
    "noindex": true
  }
}
